{
  "selectedTemplate": 1,
  "headings": {
    "work": "Work Experience",
    "education": "Education",
    "skills": "Skills",
    "projects": "Projects",
    "awards": "Awards"
  },
  "basics": {
    "name": "William Crutchfield",
    "email": "william.r.crutchfield@gmail.com",
    "phone": "2408183502",
    "website": "https://github.com/CrutchTheClutch",
    "location": {
      "address": "Santa Rosa, California"
    }
  },
  "education": [
    {
      "area": "Computer Science",
      "studyType": "BS",
      "endDate": "May 2019",
      "gpa": "3.9",
      "institution": "University of Maryland Global Campus",
      "location": "Adelphi, Maryland",
      "startDate": "Sep 2015"
    }
  ],
  "work": [
    {
      "highlights": [
        "Developed a custom ETL pipeline for Sage 300 CRE for internal migration to BuildOps.",
        "Developed internal form workflows that save hundreds of hours per month.",
        "Cut inefficiencies in IT operations that saved the company tens of thousands of dollars per year."
      ],
      "endDate": "Present",
      "company": "City Mechanical, Inc.",
      "position": "IT Manager",
      "location": "Hercules, California",
      "startDate": "November 2022"
    },
    {
      "highlights": [
        "Supported the Virtual Maintenance Trainer (VMT) projects, a collection of Unity-based virtual world maintenance trainers.",
        "Designed and developed the Operational Readiness Test System (ORTS) for the VMT projects.  Leveraged real-world big data to dynamically construct a virtual ORTS instance based on the relevant VMT project.",
        "Led a small team of developers and managed a business relationship with Lockheed Martin engineers to assist with the development of ORTS for the VMT projects.",
        "Key developer for an internal group of assemblies that increased the overall stability and development speed across all VMT projects."
      ],
      "endDate": "November 2022",
      "startDate": "February 2020",
      "location": "Dahlgren, Virginia (Remote)",
      "position": "Software Engineer I",
      "company": "Tech Wizards, Inc."
    },
    {
      "highlights": [
        "Networked with local businesses to develop small clientele for web development work.",
        "Redesigned www.masterswoodworkinginc.com leading to an increase in customer acquisition.",
        "Developed contact form workflow for www.citymechanical.com that improved turnaround for new customers."
      ],
      "company": "Self Employed",
      "position": "Freelance Web Developer",
      "location": "Remote",
      "startDate": "April 2017",
      "endDate": "Present"
    },
    {
      "highlights": [
        "Ran live recording sessions recording local artists and bands.",
        "In-house Ableton Live expert for music production, taught lessons on the software.",
        "Produced various sound cues that ended up on the shows like Venom Hunters on Discovery Channel."
      ],
      "company": "Abstract Recording Studios",
      "position": "Audio Engineer",
      "location": "Glendale, CA",
      "startDate": "January 2015",
      "endDate": "April 2017"
    }
  ],
  "skills": [
    {
      "level": "",
      "keywords": [
        "C#",
        "Typescript"
      ],
      "name": "Languages (Strong)"
    },
    {
      "keywords": [
        "Go",
        "Java",
        "SQL"
      ],
      "name": "Languages (Familiar)"
    },
    {
      "keywords": [
        "React",
        "NextJS",
        "Tailwind"
      ],
      "name": "Frameworks"
    }
  ],
  "projects": [
    {
      "keywords": [
        "TypeScript",
        "NextJS",
        "Stripe",
        "Inno Setup Compiler"
      ],
      "name": "icandrivers",
      "description": "A custom driver solution to allow the Holley Tuning Software to run on ARM-based devices.",
      "url": "https://www.icandrivers.com/"
    },
    {
      "keywords": [
        "TypeScript",
        "NextJS",
        "Stripe",
        "Convex"
      ],
      "name": "formbro",
      "url": "https://www.formbro.com/",
      "description": "A form platform intended to replace legacy providers with a easy way for non-technical businesses to leverage form workflows."
    }
  ],
  "awards": [
    {
      "title": "Dean's List",
      "date": "Fall 2015 - Spring 2019",
      "awarder": "University of Maryland Global Campus",
      "summary": "Recognized for earning a GPA of at least 3.5 in a term while completing at least 6 credits and maintained a cumulative GPA of 3.5 or higher."
    },
    {
      "title": "Magna Cum Laude",
      "date": "April 2019",
      "awarder": "University of Maryland Global Campus",
      "summary": "Recognized for graduating with a cumulative GPA of 3.901-3.999."
    }
  ],
  "sections": [
    "templates",
    "profile",
    "education",
    "work",
    "skills",
    "projects",
    "awards"
  ]
}